gencrt/__init__.py
gencrt/generalized_crt.py
gencrt/py.typed
gencrt-0.1.1.dist-info/METADATA
gencrt-0.1.1.dist-info/WHEEL
gencrt-0.1.1.dist-info/licenses/LICENSE
gencrt-0.1.1.dist-info/RECORD
