Metadata-Version: 2.4
Name: gencrt
Version: 0.1.1
Summary: A package implementing the generalized Chinese remainder theorem (CRT) algorithm.
Project-URL: Homepage, https://github.com/SL2000s/gencrt
Project-URL: Issues, https://github.com/SL2000s/gencrt/issues
Author: SL2000s
License: MIT
License-File: LICENSE
Classifier: License :: OSI Approved :: MIT License
Classifier: Operating System :: OS Independent
Classifier: Programming Language :: Python :: 3
Requires-Python: >=3.12
